synthDC/vcd/fma16.sv
// Example synthesis
module fma16 (x, y, z, mul, add, negr, negz,
	      roundmode, result);
   
   input logic [15:0]  x, y, z;   
   input logic 	       mul, add, negr, negz;
   input logic [1:0]   roundmode;
   
   output logic [15:0] result;

   // Example (not fma)
   assign result = x[7:0]*y[7:0] + z;   
 
endmodule

synthDC/vcd/create_vcd.sv
`timescale 1ps / 1ps

module tb;

   // Declare variables for stimulating input
   logic [15:0]  x, y, z;   
   logic 	       mul, add, negr, negz;
   logic [1:0]   roundmode;
   
   logic [15:0] result;
   
   logic reset, clk;
   
   // Instantiate the design block counter
  fma16 dut (x, y, z, mul, add, negr, negz,
	     roundmode, result);

   // Setup the clock to toggle every 1 time units 
   initial 
     begin	
	clk = 1'b0;
	forever #10 clk = ~clk;
     end

   initial 
     begin
	$dumpfile("fma16.vcd");
	$dumpvars (0,tb.dut);
     end
   
   initial 
     begin
	#0 reset = 1'b0;
	#10 reset = 1'b1;
	repeat (1000) 
	  begin
	     // Initialize Inputs
	     #20 x = $random;
	     #0  y = $random;
	     #0  z = $random;
	  end
	$finish();	
     end // initial begin
   
endmodule // tb

synthDC/vcd/fma16.vcd
$date
	Mon Apr 25 08:54:29 2022
$end
$version
	QuestaSim Version 2021.2
$end
$timescale
	1ps
$end

$scope module tb $end

$scope module dut $end
$var reg 16 ! x [15:0] $end
$var reg 16 " y [15:0] $end
$var reg 16 # z [15:0] $end
$var reg 1 $ mul $end
$var reg 1 % add $end
$var reg 1 & negr $end
$var reg 1 ' negz $end
$var reg 2 ( roundmode [1:0] $end
$var reg 16 ) result [15:0] $end
$upscope $end
$upscope $end
$enddefinitions $end
#0
$dumpvars
bx !
bx "
bx #
x$
x%
x&
x'
bx (
bx )
$end
#30
b11010100100100 !
b101111010000001 "
b1101011000001001 #
b1110100000101101 )
#50
b101011001100011 !
b11111101100 )
b111101100001101 "
b1101101100010000 )
b1001100110001101 #
b1001111010010100 )
#70
b1000010001100101 !
b1001111010101110 )
b101001000010010 "
b1010000010100111 )
b1110001100000001 #
b1110101000011011 )
#90
b1100110100001101 !
b1110001111101011 )
b1111000101110110 "
b1110100011111111 )
b1100110100111101 #
b1101001100111011 )
#110
b101011111101101 !
b11101001111011 )
b1111011110001100 "
b100111011011001 )
b1110100111111001 #
b110101110010101 )
#130
b10010011000110 !
b101011001000001 )
b1000010011000101 "
b1000001001010111 )
b1101001010101010 #
b110101100001000 )
#150
b1111011111100101 !
b1000001011100011 )
b111001001110111 "
b11110100011101 )
b1101011000010010 #
b100000010000101 )
#170
b1101101110001111 !
b1100010001011 )
b110100111110010 "
b101110101000000 )
b1001011011001110 #
b1110111111100 )
#190
b111101011101000 !
b111001000011110 )
b100111011000101 "
b100100101010110 )
b100100101011100 #
b1111101111100100 )
#210
b10100010111101 !
b1101101011001101 )
b101100000101101 "
b110101010010101 )
b10011001100101 #
b100011110011110 )
#230
b110001001100011 !
b11011111001100 )
b1000011100001010 "
b10101001000011 )
b10001010000000 #
b10011001011110 )
#250
b10000100100000 !
b10001111000000 )
b100010110101010 "
b11011111000000 )
b1100110010011101 #
b1110000111011101 )
#270
b11111010010110 !
b11000000111001 )
b1011100000010011 "
b1101011110111111 )
b11100000001101 #
b100001100101111 )
#290
b1101011001010011 !
b11111000110110 )
b1101110101101011 "
b101101010111110 )
b10101011010101 #
b100110110000110 )
#310
b100101000000010 !
b10101110101011 )
b11111010101110 "
b10110000110001 )
b1110100100011101 #
b1110101001111001 )
#330
b111001011001111 !
b111010111001111 )
b100100100100011 "
b10101101010 )
b110010100001010 #
b1000000101010111 )
#350
b101011001010 !
b1000000010101000 )
b100110000111100 "
b1001010001100010 )
b1011110111110010 #
b1110110101001010 )
#370
b110000110001010 !
b1101111001001010 )
b1011001101000001 "
b1110000011111100 )
b11010011011000 #
b101011111100010 )
#390
b1111001101111000 !
b101001101010000 )
b1001010001001 "
b111010100010000 )
b110111101011 #
b100111000100011 )
#410
b110010110110110 !
b110111101010001 )
b1111100111000110 "
b1001101010101111 )
b1001110101110 #
b1010000001110010 )
#430
b1010111100 !
b1010010100010110 )
b1101110100101010 "
b11001010000110 )
b1001101000001011 #
b1011100011100011 )
#450
b1011111001110001 !
b1010110010010101 )
b100000110000101 "
b1101010011000000 )
b101010101001111 #
b1001000000000100 )
#470
b110000000111011 !
b111001111110110 )
b11001100111010 "
b110001010101101 )
b11001001111110 #
b11111111011100 )
#490
b100101100010101 !
b11011101000000 )
b1001101111110001 "
b100011001000011 )
b100101111011001 #
b101111110011110 )
#510
b11101100010 !
b1010100000011011 )
b1111101101001100 "
b110100011110001 )
b101010110011111 #
b111001010110111 )
#530
b1010000110001111 !
b1000000000010011 )
b1010100111111000 "
b1110000000100111 )
b110000010110111 #
b1110101100111111 )
#550
b101011010011111 !
b1111101010111111 )
b1001010001011100 "
b1001100111011011 )
b1100000001011011 #
b1111100101111111 )
#570
b11011110001001 !
b1111000110010111 )
b11001001001001 "
b1110011101101100 )
b11111011010000 #
b110010111100001 )
#590
b1100000011010111 !
b111110000011111 )
b1111110001010001 "
b1000001011010111 )
b10111110010110 #
b111001110011101 )
#610
b111111100001100 !
b11001101100010 )
b1100111011000010 "
b11100010101110 )
b1110110111001000 #
b1111011011100000 )
#630
b101101001110111 !
b100011111110110 )
b1110110100111101 "
b101000100011 )
b1101101100010010 #
b1111011101101101 )
#650
b1111110 !
b1111100100011000 )
b1000000101101101 "
b1000010111000 )
b1110011100111001 #
b1110011011111 )
#670
b1000111100011111 !
b1111010001101100 )
b1111011011010011 "
b11000110 )
b10111110000101 #
b100100100010010 )
#690
b1000100001111000 !
b1001001001101101 )
b101100101011011 "
b101101000101101 )
b100101101001001 #
b111010111110001 )
#710
b1010111000111111 !
b110000110101110 )
b1010111100101010 "
b101010110011111 )
b110001101011000 #
b110110110101110 )
#730
b11100010000110 !
b111100101010100 )
b110010001110 "
b1010110110101100 )
b1111001010011100 #
b11110011110000 )
#750
b1001100111111010 !
b111110101001000 )
b1011110000100110 "
b1011110111000 )
b1011101110011 #
b11110010001111 )
#770
b1011010010100011 !
b10111110100101 )
b1010100000101111 "
b11010101100000 )
b1001001010110011 #
b1011000010100000 )
#790
b101011001011111 !
b1010010000100100 )
b110101000100 "
b1010101111101111 )
b1111110111110111 #
b1011100110011 )
#810
b11011011001011 !
b11001111100011 )
b1101011100110 "
b1011010001011001 )
b1101101101011010 #
b1001000110111100 )
#830
b1100000100101001 !
b110000 )
b1110001011101101 "
b101001111 )
b110110011011010 #
b1001001011001111 )
#850
b1011011001100101 !
b1100101001011011 )
b1110001010110101 "
b1011010001000011 )
b1001010011011111 #
b1101110001001000 )
#870
b1100101111001 !
b1110101001101100 )
b1111111101000100 "
b1011010100000011 )
b110011010000 #
b10110011110100 )
#890
b101100101010 !
b1011111111000 )
b1010110110101011 "
b10100011011110 )
b1100111100001110 #
b1110101100011100 )
#910
b1010110111011100 !
b110001000000010 )
b1011110010011010 "
b101001101100110 )
b111001011111101 #
b1111011101010101 )
#930
b1011000011 !
b1110100001001011 )
b1110110101010110 "
b1011010001111111 )
b1110100101001110 #
b10101011010000 )
#950
b111011001100111 !
b101111101000 )
b11010000001010 "
b1110110101010100 )
b1011100110110110 #
b1011110110111100 )
#970
b1000101000111000 !
b1011101111100110 )
b1000011101111001 "
b1101010000101110 )
b1100010010111000 #
b1101111100110000 )
#990
b1011111110010100 !
b101010101100 )
b101110110010011 "
b1100110110100 )
b10110000000100 #
b1000000100000000 )
#1010
b1100101001011001 !
b101111100011111 )
b110100111011011 "
b111100000100111 )
b1101111001001101 #
b10101001110000 )
#1030
b1011011111011001 !
b1001011111110000 )
b10011001101101 "
b11101010110010 )
b1110001001110110 #
b11111011011011 )
#1050
b100100111001010 !
b11100001111000 )
b10110110110110 "
b111001000010010 )
b111000110010101 #
b100110001 )
#1070
b1101001000110 !
b1010001101011001 )
b1001101100000100 "
b111001010101101 )
b110000111110111 #
b110001100001111 )
#1090
b11101101001 !
b110001110011011 )
b1011101010110100 "
b1010101111001011 )
b1000110110001000 #
b1101011101011100 )
#1110
b1101100100101000 !
b1010100110101000 )
b10000101101 "
b1001010010010000 )
b11000011000111 #
b11011111001111 )
#1130
b1001110000101110 !
b11100011011101 )
b1110010000001000 "
b11001000110111 )
b100010100011100 #
b100011010001100 )
#1150
b1010011011111101 !
b100110100000100 )
b11100101001 "
b110110110100001 )
b1001000000011100 #
b1011100010100001 )
#1170
b110011110000110 !
b1010010110010010 )
b100011011010 "
b1000111000 )
b1100011000111101 #
b11100001011001 )
#1190
b1010011101100110 !
b1110100011001 )
b1100010001110000 "
b1111001011011101 )
b10001110011 #
b11000100010011 )
#1210
b1001100110111010 !
b101010111010011 )
b1011001101011110 "
b100100010111111 )
b111100111111010 #
b1011111001000110 )
#1230
b10111010101 !
b1100100000110000 )
b1111011000011010 "
b1000111110011100 )
b10111001 #
b1011001011011 )
#1250
b110000100110111 !
b11001001111 )
b11011110010110 "
b10000011110011 )
b10000111000000 #
b100000111111010 )
#1270
b1001111100100110 !
b11100000000100 )
b1101010110110 "
b11110011000100 )
b1000001101111101 #
b1001111010000001 )
#1290
b111111011100 !
b1111111100101 )
b101011110000110 "
b1111011010100101 )
b1111111101111000 #
b111001010100000 )
#1310
b1001101101111110 !
b100000101101100 )
b1000000011011011 "
b110101101000010 )
b1011011011001111 #
b10001010011001 )
#1330
b10101101111001 !
b1111001010010 )
b1110010011111010 "
b10110011111001 )
b1110111001100001 #
b110010010001011 )
#1350
b100100010111 !
b10011010111 )
b111100010100001 "
b1111110011011000 )
b1001000110000110 #
b1001111111111101 )
#1370
b1001011001010000 !
b1100001111010110 )
b101100111110101 "
b1101111000010110 )
b1000100000110101 #
b1101010011000101 )
#1390
b1000101000101001 !
b1010111101110010 )
b111010111000001 "
b1010011100011110 )
b111010011000101 #
b1001001110101110 )
#1410
b1011010010011000 !
b1110011101011101 )
b111101101001011 "
b1010000101001101 )
b100001001110011 #
b110111011111011 )
#1430
b1110011011101100 !
b1000011110010111 )
b1011010001010 "
b1100000110101011 )
b1101000101001110 #
b101000010000110 )
#1450
b1000000010101000 !
b10101111011110 )
b1111110110101001 "
b100000000110110 )
b1000110010100001 #
b1111101110001001 )
#1470
b1011100100001110 !
b1001010111011111 )
b110011011100110 "
b1001100100110101 )
b1100000010011111 #
b1100110100110011 )
#1490
b1011010100101010 !
b1110011001011011 )
b1110100101010 "
b1100011110000011 )
b1111010010001101 #
b1111101101110001 )
#1510
b1111111110011110 !
b111001111001 )
b1110011000111000 "
b1011100011101 )
b1010100001111001 #
b1100101100001001 )
#1530
b1110001111001000 !
b1101010000111001 )
b100010111001010 "
b100011001001001 )
b100000100010011 #
b1101111011100011 )
#1550
b1100100101101011 !
b1001010110000001 )
b1010111011000111 "
b1001010001000000 )
b1101110110110110 #
b11000011100011 )
#1570
b1001110110111010 !
b110111001001100 )
b1010101111000100 "
b110110000011110 )
b1001010110111001 #
b10010000100001 )
#1590
b1101001110010010 !
b10110000001 )
b1001101010110100 "
b1111110001100001 )
b11101101111111 #
b1010001000100111 )
#1610
b1001000010000110 !
b1001100110110111 )
b1111010111111010 "
b1011111001011011 )
b1001010011110010 #
b1011111001110 )
#1630
b10000100110010 !
b1100010111000110 )
b101111010111101 "
b1011100111011100 )
b1100110110000100 #
b1111001001101110 )
#1650
b1010010011100100 !
b111010111011000 )
b1100111111001010 "
b1000000101101100 )
b111100110101001 #
b10110110010001 )
#1670
b1010100010100001 !
b1111100010110011 )
b1010100110001110 "
b1101001011110111 )
b110101011111011 #
b1100010001001001 )
#1690
b1111000001011 !
b111000100010101 )
b1001000011101111 "
b111010101000000 )
b11110111001001 #
b100100000001110 )
#1710
b1110010100110110 !
b111000000110011 )
b100100001110101 "
b101011001110111 )
b101011010001111 #
b110111100111101 )
#1730
b1011111101101011 !
b1000011101110110 )
b1110011110001000 "
b1000111101100111 )
b1011010010101110 #
b1110110110000110 )
#1750
b1000000110011011 !
b11100000110 )
b100010110010010 "
b110100010100 )
b1101111100101000 #
b11011110001110 )
#1770
b1110000000101101 !
b1111100011010010 )
b101111101001011 "
b1110110001010111 )
b1011000011000010 #
b1011110111110001 )
#1790
b1111011000011110 !
b1011100110001100 )
b10100001101 "
b1011001001001000 )
b1111110111101100 #
b1111111101110010 )
#1810
b1001110100011000 !
b1111111100100100 )
b1101111010001 "
b1000110000100 )
b1110010000110 #
b11000000011110 )
#1830
b10010001000001 !
b101000110010111 )
b110010000111011 "
b10101110000001 )
b1111100111011000 #
b100011010011 )
#1850
b1110100101010011 !
b110011111001 )
b110001001010110 "
b1010110111010 )
b10001001011011 #
b11111000111101 )
#1870
b1111101011100010 !
b110111001000111 )
b1110001000000100 "
b10010111100011 )
b1101110011 #
b11011111011 )
#1890
b1011010011011000 !
b11011010011 )
b100110100010010 "
b1001010100011 )
b100010010111000 #
b101001111101000 )
#1910
b1001000111001 !
b100100010111010 )
b1011011011100101 "
b111011110110101 )
b1101110010100001 #
b111110011110 )
#1930
b111100101011 !
b1100011000 )
b101110110000001 "
b1111001001001100 )
b1000010111001000 #
b1001101101110011 )
#1950
b101010100100111 !
b1001100101101111 )
b1111100110100001 "
b1001111001001111 )
b110111000011111 #
b1000011010100110 )
#1970
b11101000000100 !
b111000010100011 )
b10001101011000 "
b110111101111111 )
b1000000010010110 #
b1000000111110110 )
#1990
b1001001100010100 !
b1000011101110110 )
b1011010000010010 "
b1000000111111110 )
b111000010010110 #
b111000111111110 )
#2010
b1110001010110001 !
b111110100001000 )
b1101010101010101 "
b1010101101011011 )
b1000111011101101 #
b1100100110110010 )
#2030
b10101100101011 !
b1001110100110100 )
b1101111110101 "
b1011100000010100 )
b1110101101 #
b10110011010100 )
#2050
b10001000100111 !
b10100100000000 )
b1111111110000100 "
b1011111001001 )
b1110010010100111 #
b1111100011000011 )
#2070
b1010011011100111 !
b101101111000011 )
b1001000010111001 "
b1000101110010110 )
b101011001001001 #
b1111110100111000 )
#2090
b1011101111011011 !
b1111010010001100 )
b111111001001 "
b1000111100 )
b1011000101010001 #
b101110101000100 )
#2110
b101111010100001 !
b10111110111010 )
b1101110100101010 "
b1100101110111011 )
b100010111111010 #
b110000001100100 )
#2130
b10000001000101 !
b101000101001100 )
b10110000011 "
b110100101001001 )
b100001001111100 #
b110010111001011 )
#2150
b1010001110010 !
b111110011010010 )
b11110011111110 "
b1011001110011000 )
b1111001001101000 #
b110001110000100 )
#2170
b1010101001101111 !
b110000010001010 )
b110110000110 "
b10110010000010 )
b10000111110000 #
b101110000001010 )
#2190
b1001011100111000 !
b11111101000000 )
b1001000101000000 "
b10111111110000 )
b111011000101000 #
b1000010000101000 )
#2210
b1010100111110110 !
b1011001110101000 )
b1101011000101 "
b11001101110110 )
b11000111000000 #
b1110111100001110 )
#2230
b101111101110100 !
b1000101100000100 )
b111000100111001 "
b100101110010100 )
b110101010110000 #
b1000010010000100 )
#2250
b1000011100111100 !
b111100000001100 )
b1001001100101010 "
b111010010001000 )
b1101001101100010 #
b1101110100111010 )
#2270
b11010100010101 !
b1101011011010100 )
b100111011100001 "
b1110010111010111 )
b1001110100010111 #
b1010111110001100 )
#2290
b1110111001000011 !
b1101011111111010 )
b1110001111001001 "
b1101000110110010 )
b10010000110 #
b11100100100001 )
#2310
b1100101100100101 !
b10000110010011 )
b1001110111000001 "
b10000001101011 )
b1010001010001101 #
b1011111001110010 )
#2330
b1110001001011010 !
b1110011001100111 )
b10011100000111 "
b1010010100000011 )
b111101100101100 #
b111110110100010 )
#2350
b101110100001100 !
b111101110000000 )
b1110011001110001 "
b1000000001111000 )
b111110000111011 #
b1000000110000111 )
#2370
b1110010110110110 !
b1100110010010001 )
b1100001011110111 "
b10101111010101 )
b1100111010011110 #
b111111000111000 )
#2390
b101100001011100 !
b10011101100010 )
b1111011101010101 "
b1110110100101010 )
b11101000100000 #
b101100010101100 )
#2410
b1001010100000 !
b110111101000000 )
b100101110010 "
b1000000101100000 )
b1000110010110100 #
b1101001111110100 )
#2430
b1111010111011101 !
b1110111100011110 )
b1111000000001101 "
b1001011111101101 )
b1001100101001011 #
b1010010010000100 )
#2450
b100001001111001 !
b1001111101110000 )
b1101101010011110 "
b1110001111111001 )
b110010011111101 #
b1010111110101011 )
#2470
b1101001001111011 !
b1011000011100111 )
b111001110001111 "
b1010100110110010 )
b1001101000000011 #
b1101111010111000 )
#2490
b10100111100011 !
b1100011010000 )
b100001100011101 "
b1011001110111010 )
b11110110110001 #
b101011101101000 )
#2510
b1001111101000100 !
b100010101100101 )
b1011110010010101 "
b110010101000101 )
b11010011100000 #
b101110001110100 )
#2530
b111100011101101 !
b1011111011010001 )
b1010101010010 "
b1000000011001010 )
b101101111111000 #
b1010011111100010 )
#2550
b1011011110001101 !
b1000100100100010 )
b1100010001010010 "
b1110011110000100 #
b1010010101110 )
#2570
b1111110101000110 !
b1111110111110000 )
b1001001010001100 "
b110111001100 )
b111110110010000 #
b1010001111011000 )
#2590
b1100000100010111 !
b1000101000100100 )
b110000101101010 "
b1000011100010110 )
b101011110000100 #
b110000100001010 )
#2610
b1011110010101010 !
b1001110111101000 )
b111101111100 "
b1010100111011100 )
b1001100000 #
b101010010111000 )
#2630
b100110110111010 !
b101110001111000 )
b110000010001011 "
b110011101011110 )
b1111111010100110 #
b110001110100100 )
#2650
b1111000100101 !
b1001010111101 )
b1000001100110010 "
b10111100000 )
b10010100010 #
b101111011100 )
#2670
b111110001001001 !
b1001011100100 )
b1011000000010100 "
b101001010110 )
b1100000000111101 #
b1100010111110001 )
#2690
b1101001011 !
b1100011000011001 )
b11000001011100 "
b1101101100110001 )
b111010101000111 #
b1001000000111011 )
#2710
b1001011110000110 !
b1010010101101111 )
b111101000111001 "
b1001001100011101 )
b1000101010110100 #
b1010100010001010 )
#2730
b1110010111010000 !
b1011100100000100 )
b101000000101100 "
b1010111001110100 )
b100010110001100 #
b110100101001100 )
#2750
b1011011100000111 !
b100011011000000 )
b100000001101010 "
b100100001110010 )
b1111100100010001 #
b1111101111110111 )
#2770
b1111111111101000 !
b101100100100001 )
b1001111001001011 "
b11110100001001 )
b1000000101110011 #
b1100010101101011 )
#2790
b101101111101100 !
b1100011010010111 )
b10100100011 "
b1010000110110111 )
b1110111110100100 #
b111111101000 )
#2810
b110010111001001 !
b101100011111 )
b10000111001 "
b1110001100101 )
b111001011011111 #
b1001111110100000 )
#2830
b1010011010100 !
b1010001000010011 )
b110010101100111 "
b1100100000101011 )
b100000110011101 #
b1001011011101001 )
#2850
b10010110110000 !
b1000100001101101 )
b11100110000010 "
b1001101011111101 )
b1011111101001001 #
b1100010101001 )
#2870
b1101011011001 !
b10110101111011 )
b1011011100100000 "
b1101101001101001 )
b100110000011100 #
b110011100111100 )
#2890
b110111110010011 !
b101111001111100 )
b110000111100011 "
b1100111001110101 )
b1000001000101010 #
b10010000011 )
#2910
b1111100011001000 !
b11001110000010 )
b10111001011101 "
b1100101011010010 )
b1001110100111010 #
b1110010111100010 )
#2930
b1010100110000100 !
b1100110100101110 )
b1010100000101011 "
b1011001101100110 )
b111111100111001 #
b1001010101100101 )
#2950
b1110000010010 !
b1000001000111111 )
b1010010 "
b1000010011111101 )
b1000100101011001 #
b1000111100011101 )
#2970
b1001011011010000 !
b1100101111111001 )
b1110101001101110 "
b1110001010111001 )
b10100110010111 #
b1000001011110111 )
#2990
b1000011111011011 !
b1000011110110001 )
b111011110100110 "
b1011011110011001 )
b1101001110111011 #
b110000110111101 )
#3010
b111110000000000 !
b1101001110111011 )
b100110000001111 "
b1101011001101001 #
b1101011001101001 )
#3030
b110001000001100 !
b1101011100011101 )
b1100101011001 "
b1101101010010101 )
b100100111000101 #
b100110111110001 )
#3050
b11010111001111 !
b1001000110111100 )
b1110010110010000 "
b1011111000110101 )
b1101100001010001 #
b100110011000001 )
#3070
b1010010001101001 !
b1001101100001 )
b1100110101110111 "
b100100100000 )
b110010101001010 #
b1001011000011001 )
#3090
b101100011011000 !
b1100100110110010 )
b100110110011011 "
b1110100000010010 )
b1001101011000100 #
b1110110001100 )
#3110
b1011000110111000 !
b101000101100 )
b1111001010110111 "
b1111001001100 )
b1110111010000110 #
b111001000001110 )
#3130
b101101000110000 !
b1000011010110 )
b101001101110111 "
b10011010110 )
b1100011110110101 #
b1101111000000101 )
#3150
b1111010111010100 !
b10101001000001 )
b1000011100000111 "
b1100110110000001 )
b1001011101110110 #
b1001110101000010 )
#3170
b1010110111101001 !
b1001110111010101 )
b1000101110001011 "
b1010111111001 )
b101111100000001 #
b1101110110000100 )
#3190
b1000101111011011 !
b1101010111101010 )
b100001010000000 "
b1100110010000001 )
b1001111111000010 #
b110101000010 )
#3210
b1101101011000101 !
b1001000010 )
b1111101000110000 "
b1100010010110010 )
b1110010010101111 #
b100110011111 )
#3230
b1101101001100110 !
b1111011111001111 )
b1011100110101111 "
b10101001101001 )
b110111011101001 #
b1011010010100011 )
#3250
b1010111111111000 !
b1100001110001 )
b1010110000000110 "
b111010010111001 )
b111011011101111 #
b111110010111111 )
#3270
b11011111100001 !
b111110000110101 )
b111110010010101 "
b1111100111100100 )
b11111011101110 #
b1100000111100011 )
#3290
b100110101100000 !
b111011011001110 )
b101111011100101 "
b1001010011001110 )
b1110101000101000 #
b100000000001000 )
#3310
b111110101100100 !
b100001110011100 )
b11011100101001 "
b1111101000101100 )
b1010111011100001 #
b1011111011100101 )
#3330
b101001001110111 !
b1100000111110000 )
b1010101101110 "
b1110001000000011 )
b1111010110000001 #
b10100010100011 )
#3350
b1011100111010101 !
b101000100000111 )
b1101010101101000 "
b100110000001001 )
b111000111110000 #
b1100100001111000 )
#3370
b10101010 !
b1011011100000000 )
b1100001100001111 "
b111101111100110 )
b100100011110001 #
b101001011100111 )
#3390
b1011110001111101 !
b101000001000100 )
b1001010110001110 "
b1000111001000111 )
b1101110011100010 #
b10001000111000 )
#3410
b100110100111100 !
b1111111000101010 )
b1110011010101001 "
b10001111110 )
b1011000111101111 #
b1101100110001011 )
#3430
b1101000001011011 !
b1110111000000010 )
b11110010101111 "
b1111000000100100 )
b1001101101001010 #
b1101100101111111 )
#3450
b110110111001 !
b1100111000001 )
b10110100010011 "
b1010100100000101 )
b11010100010011 #
b100001011001110 )
#3470
b100000101100101 !
b11110010010010 )
b10011101010001 "
b101010100001000 )
b11101010110111 #
b101101010101100 )
#3490
b1000010011001 !
b110101100100000 )
b100000111010 "
b101110101100001 )
b11101001110001 #
b101110100011011 )
#3510
b11101100010 !
b101000010100101 )
b110101011100100 "
b1001000110111001 )
b1101110100101010 #
b11010001110010 )
#3530
b100010001111101 !
b100110001111110 )
b101111101011001 "
b100010011111 )
b1010001111100101 #
b1100111101011010 )
#3550
b110101111101101 !
b1111011001001010 )
b11001001 "
b101110111111010 )
b1100110001000001 #
b1000011001010110 )
#3570
b1101000110101111 !
b101010110101000 )
b1110011011011 "
b110000111110110 )
b1110100011001101 #
b111111010000010 )
#3590
b1001111101110000 !
b100100010011101 )
b1101010000000110 "
b1110101101101101 )
b10000010100010 #
b10001101000010 )
#3610
b11110110111101 !
b10010100010000 )
b1101111001101010 "
b110111011100100 )
b100011111011100 #
b1001011000011110 )
#3630
b101111001010000 !
b110100011111100 )
b1111010001111011 "
b110111001001100 )
b101100000100101 #
b111111010010101 )
#3650
b1000010001111000 !
b1001000111001101 )
b1000100111110110 "
b1100101101110101 )
b1100111001011100 #
b100000110101100 )
#3670
b1001101100100011 !
b1110111111111110 )
b1010101101111001 "
b1101111011100111 )
b10111001000 #
b1011001010011 )
#3690
b100011010111011 !
b101111000101011 )
b1110111000001110 "
b1000000000010 )
b1001010001110011 #
b1001111010101101 )
#3710
b1100001100 !
b1001010100011011 )
b1001100011001110 "
b1001111000011011 )
b110000111010100 #
b110101101111100 )
#3730
b1101110001011001 !
b1010100101110010 )
b110111110111001 "
b1010001000100101 )
b1100000010110011 #
b100000100 )
#3750
b1011111111110100 !
b111000100000111 )
b1110001001110101 "
b11000000110111 )
b1111000100001100 #
b110000010010000 )
#3770
b111101000111001 !
b101100011001 )
b1001001100000010 "
b1111000101111110 )
b1011111000010101 #
b1011111010000111 )
#3790
b1111100100000101 !
b1011111000011111 )
b100001101001110 "
b1011111110011011 )
b10100100000010 #
b10101010001000 )
#3810
b101000110111000 !
b110000100010010 )
b1011001000001000 "
b10111011000010 )
b101001110001101 #
b101100101001101 )
#3830
b1000111010101111 !
b101100100000101 )
b11000111101000 "
b1111001000100101 )
b100110010000 #
b1010100000101000 )
#3850
b1010101111110101 !
b1110011110011000 )
b1001000001001100 "
b101001001001100 )
b1011110101111011 #
b11000110111 )
#3870
b1010011001000000 !
b1101000001111011 )
b1100100101 "
b1100011010111011 )
b1011011000001101 #
b1011111101001101 )
#3890
b1000001110000 !
b1100011000111101 )
b1111100100101101 "
b1100100110111101 )
b1101100000101001 #
b1110101111011001 )
#3910
b101000110111100 !
b1111100100110101 )
b100000110000 "
b1111101101101001 )
b10110111000000 #
b101000100000000 )
#3930
b110100101010000 !
b11110011000000 )
b110101010100001 "
b110000000010000 )
b11111101001101 #
b111000110011101 )
#3950
b10111011110101 !
b1101100101100010 )
b1010111111110101 "
b10100111000110 )
b1100110001011101 #
b1011011011010110 )
#3970
b1001010010100 !
b101101000000001 )
b1010011001101010 "
b100110100101 )
b110010110111100 #
b1010001100000100 )
#3990
b100010111000 !
b1011000111101100 )
b1001110010011110 "
b1101011101001100 )
b11011111010 #
b111100010001010 )
#4010
b101101000110 !
b11001000101110 )
b110010000000111 "
b100011100100 )
b1011110010010011 #
b1011111001111101 )
#4030
b111010001010101 !
b1011111011100110 )
b1101101110110111 "
b1111100101010110 )
b1111000101000101 #
b10111000001000 )
#4050
b101001100011 !
b11100000001010 )
b1110000001011001 "
b1001110110000 )
b1100111000100110 #
b1111000010010001 )
#4070
b111011001101000 !
b1111001001001110 )
b1110010000011110 "
b1101101001010110 )
b1111010010010000 #
b11000000 )
#4090
b1010010101011010 !
b1111111100011100 )
b1000010100011100 "
b1111111001101000 )
b110011110111001 #
b111000110010001 )
#4110
b1111110101011 !
b111101001101101 )
b1101100111010000 "
b1111001010101001 )
b110010101101111 #
b1111000001011111 )
#4130
b110110111011000 !
b1010011101111 )
b1000100001000101 "
b1001111110100111 )
b1010011110001101 #
b1110000111000101 )
#4150
b10001110001011 !
b1100110100000100 )
b1001000111111100 "
b11000001100001 )
b1111111011100 #
b1010100010110000 )
#4170
b101010100100 !
b1100000101001100 )
b1000110100011001 "
b10111111100000 )
b11001110100101 #
b100001110101001 )
#4190
b1000111000111110 !
b11100110110011 )
b1100000011110011 "
b110111001111111 )
b10110001011000 #
b110011100110010 )
#4210
b110101111000100 !
b1110011001100100 )
b100001101011100 "
b111001011001000 )
b100010100000110 #
b1000101101110110 )
#4230
b101000010011010 !
b111110001011110 )
b1100100011000 "
b101001101110110 )
b110011011000101 #
b111010100110101 )
#4250
b1101000110101010 !
b111011010110101 )
b1100011010 "
b111100000001001 )
b1101010111000011 #
b1110011100000111 )
#4270
b1110100110110010 !
b1110011111010111 )
b110001100001100 "
b1101111000011011 )
b111011101001 #
b1011101000001 )
#4290
b1111110111000011 !
b1100000001101 )
b111001111101011 "
b1100000111101010 )
b1011100111111000 #
b110110011111001 )
#4310
b1111110010 !
b1001100000011110 )
b1010110110001001 "
b11101101111010 )
b111001101101111 #
b1111010011110001 )
#4330
b100101100011011 !
b1000000111100010 )
b10100010101101 "
b1000010110101110 )
b1100000101101000 #
b1101001110100111 )
#4350
b1001000100101 !
b1101101001101001 )
b101011111001111 "
b1101111101010011 )
b1000110110101011 #
b1010101110010110 )
#4370
b1101001000011011 !
b1010001110000000 )
b11111010000000 "
b1001101100101011 )
b1101100101011101 #
b1110011011011101 )
#4390
b1111110110000010 !
b1101001011101 )
b100001000000100 "
b1101101101100101 )
b1010010101010111 #
b1010011101011111 )
#4410
b1000101100110110 !
b1010011000101111 )
b1100110010 "
b1010111111100011 )
b10100001111001 #
b11001100000101 )
#4430
b1010111011100100 !
b101010100000001 )
b1110110000010110 "
b11110000010001 )
b1110110010101010 #
b1000010 )
#4450
b110010111000000 !
b1111110100101010 )
b1000100000101110 "
b111100101010 )
b11011110001100 #
b101101000001100 )
#4470
b1100001001110001 !
b100101111011010 )
b1000111111111011 "
b1010011001010111 )
b10000110111100 #
b1001000010000111 )
#4490
b110100011011100 !
b1111100101110000 )
b101011100010111 "
b11010110000000 )
b10011000001 #
b1100010000101 )
#4510
b10000111101011 !
b1100111011110 )
b11101110110101 "
b1010101011101000 )
b10111010001001 #
b1101010010110000 )
#4530
b1110001010001111 !
b1001001110100100 )
b1111011010111111 "
b1001100100111010 )
b10101010110000 #
b1001010101100001 )
#4550
b1001101011010011 !
b1100100000011101 )
b1011010110 "
b1101101100010010 )
b1100110010000010 #
b111110011100100 )
#4570
b111010100011010 !
b1110001000111110 )
b1010011101110001 "
b1101011111111100 )
b10011010111 #
b1000001010001 )
#4590
b1000111000001110 !
b101100000101 )
b1010011110001 "
b1001000000101 )
b1110111001101 #
b10101011111011 )
#4610
b100001100000101 !
b10001010000010 )
b1110101100011100 "
b1111001011001 )
b1100011110011000 #
b1100100000100100 )
#4630
b1000100011101100 !
b1110000101101000 )
b1101011000101010 "
b1110111001010000 )
b100101001100101 #
b111000100011101 )
#4650
b10100110111 !
b101001101101011 )
b11011000000011 "
b100101100001010 )
b1001111011111110 #
b1001111110100011 )
#4670
b1101110011111101 !
b1010000111110101 )
b111000111110 "
b1101110001000100 )
b11010011101000 #
b111001000101110 )
#4690
b11100001110100 !
b101000100000000 )
b1000100110110000 "
b1000010010101000 )
b1101110000000110 #
b10101111000110 )
